hewo/__init__.py
hewo/main/__init__.py
hewo/main/endpoint.py
hewo/main/main.py
hewo/main/window.py
hewo/objects/__init__.py
hewo/objects/hewo/__init__.py
hewo/objects/hewo/eye.py
hewo/objects/hewo/eye_components.py
hewo/objects/hewo/face.py
hewo/objects/hewo/hewo.py
hewo/objects/hewo/mouth.py
hewo/objects/hewo/logic/__init__.py
hewo/objects/hewo/logic/emotion_mapper.py
hewo/objects/hewo/logic/input_handler.py
hewo/objects/multimedia/__init__.py
hewo/objects/multimedia/multimedia.py
hewo/resources/img.png
hewo/resources/test.mp4
hewo/settings/__init__.py
hewo/settings/hewo/__init__.py
hewo/settings/hewo/eye.yaml
hewo/settings/hewo/face.yaml
hewo/settings/hewo/mouth.yaml
hewo/settings/multimedia/__init__.py
hewo/settings/multimedia/multimedia.yaml
hewo/settings/window/__init__.py
hewo/settings/window/main.yaml
hewo-0.3.1.dist-info/licenses/LICENSE
hewo-0.3.1.dist-info/METADATA
hewo-0.3.1.dist-info/WHEEL
hewo-0.3.1.dist-info/entry_points.txt
hewo-0.3.1.dist-info/top_level.txt
hewo-0.3.1.dist-info/RECORD
